pyapep/__init__.py
pyapep/isofit.py
pyapep/simide.py
pyapep/simsep.py
pyapep/simsep_backup.py
pyapep-0.1.8.dist-info/METADATA
pyapep-0.1.8.dist-info/WHEEL
pyapep-0.1.8.dist-info/top_level.txt
pyapep-0.1.8.dist-info/RECORD
