Metadata-Version: 2.1
Name: pyapep
Version: 0.1.8
Summary: Python package for adsorption process simulations
Home-page: https://sebygaa.github.io/pyAPEP/
Author: Seongbin Ga
Author-email: sgasga@ulsan.ac.kr
Requires-Python: >=3.6
Requires-Dist: numpy>=1.20.0
Requires-Dist: scipy>=1.5.0
Requires-Dist: matplotlib>=3.0.0
